ahocorasick_rs-1.0.3.dist-info/METADATA
ahocorasick_rs-1.0.3.dist-info/WHEEL
ahocorasick_rs-1.0.3.dist-info/licenses/LICENSE
ahocorasick_rs/__init__.py
ahocorasick_rs/ahocorasick_rs.cpython-314t-aarch64-linux-gnu.so
ahocorasick_rs/ahocorasick_rs.pyi
ahocorasick_rs/py.typed
ahocorasick_rs-1.0.3.dist-info/RECORD
